pyaat/__init__.py
pyaat/aircraft.py
pyaat/atmosphere.py
pyaat/constants.py
pyaat/flightmechanics.py
pyaat/gravity.py
pyaat/performance.py
pyaat/propulsion.py
pyaat/pyaatcontrol.py
pyaat/system.py
pyaat/tools.py
pyaat/wind.py
PyAAT-0.0.dev10.dist-info/LICENSE
PyAAT-0.0.dev10.dist-info/METADATA
PyAAT-0.0.dev10.dist-info/WHEEL
PyAAT-0.0.dev10.dist-info/top_level.txt
PyAAT-0.0.dev10.dist-info/RECORD
