Metadata-Version: 2.1
Name: PyAAT
Version: 0.0.dev10
Summary: Python Aerospace Analysis Toolbox
Home-page: https://github.com/KenedyMatiasso/PyAAT
Author: Kenedy Matiassp Portella
Author-email: kenedyportella@hotmail.com
License: MIT
License-File: LICENSE
Requires-Dist: numpy
Requires-Dist: scipy
Requires-Dist: matplotlib
Requires-Dist: control
